[
null,
{"id":1,"members":[{"enemyId":1,"x":144,"y":480,"hidden":false},{"enemyId":2,"x":352,"y":544,"hidden":false},{"enemyId":2,"x":96,"y":640,"hidden":false}],"name":"Easy Troops 1","pages":[{"conditions":{"actorHp":50,"actorId":1,"actorValid":false,"enemyHp":50,"enemyIndex":0,"enemyValid":false,"switchId":1,"switchValid":false,"turnA":0,"turnB":0,"turnEnding":true,"turnValid":false},"list":[{"code":111,"indent":0,"parameters":[4,10,0]},{"code":117,"indent":1,"parameters":[101]},{"code":0,"indent":1,"parameters":[]},{"code":411,"indent":0,"parameters":[]},{"code":115,"indent":1,"parameters":[]},{"code":0,"indent":1,"parameters":[]},{"code":412,"indent":0,"parameters":[]},{"code":0,"indent":0,"parameters":[]}],"span":1}]},
{"id":2,"members":[{"enemyId":4,"x":208,"y":496,"hidden":false},{"enemyId":5,"x":208,"y":688,"hidden":false}],"name":"Easy Troops 2","pages":[{"conditions":{"actorHp":50,"actorId":1,"actorValid":false,"enemyHp":50,"enemyIndex":0,"enemyValid":false,"switchId":1,"switchValid":false,"turnA":0,"turnB":0,"turnEnding":true,"turnValid":false},"list":[{"code":111,"indent":0,"parameters":[4,10,0]},{"code":117,"indent":1,"parameters":[101]},{"code":0,"indent":1,"parameters":[]},{"code":411,"indent":0,"parameters":[]},{"code":115,"indent":1,"parameters":[]},{"code":0,"indent":1,"parameters":[]},{"code":412,"indent":0,"parameters":[]},{"code":0,"indent":0,"parameters":[]}],"span":1}]},
{"id":3,"members":[{"enemyId":3,"x":160,"y":464,"hidden":false},{"enemyId":2,"x":112,"y":624,"hidden":false},{"enemyId":1,"x":384,"y":528,"hidden":false}],"name":"Easy Troops 3","pages":[{"conditions":{"actorHp":50,"actorId":1,"actorValid":false,"enemyHp":50,"enemyIndex":0,"enemyValid":false,"switchId":1,"switchValid":false,"turnA":0,"turnB":0,"turnEnding":true,"turnValid":false},"list":[{"code":111,"indent":0,"parameters":[4,10,0]},{"code":117,"indent":1,"parameters":[101]},{"code":0,"indent":1,"parameters":[]},{"code":411,"indent":0,"parameters":[]},{"code":115,"indent":1,"parameters":[]},{"code":0,"indent":1,"parameters":[]},{"code":412,"indent":0,"parameters":[]},{"code":0,"indent":0,"parameters":[]}],"span":1}]},
{"id":4,"members":[{"enemyId":4,"x":224,"y":496,"hidden":false},{"enemyId":6,"x":160,"y":656,"hidden":false}],"name":"Easy Troops 4","pages":[{"conditions":{"actorHp":50,"actorId":1,"actorValid":false,"enemyHp":50,"enemyIndex":0,"enemyValid":false,"switchId":1,"switchValid":false,"turnA":0,"turnB":0,"turnEnding":true,"turnValid":false},"list":[{"code":111,"indent":0,"parameters":[4,10,0]},{"code":117,"indent":1,"parameters":[101]},{"code":0,"indent":1,"parameters":[]},{"code":411,"indent":0,"parameters":[]},{"code":115,"indent":1,"parameters":[]},{"code":0,"indent":1,"parameters":[]},{"code":412,"indent":0,"parameters":[]},{"code":0,"indent":0,"parameters":[]}],"span":1}]},
{"id":5,"members":[{"enemyId":8,"x":224,"y":496,"hidden":false},{"enemyId":1,"x":176,"y":670,"hidden":false}],"name":"Easy Troops 5","pages":[{"conditions":{"actorHp":50,"actorId":1,"actorValid":false,"enemyHp":50,"enemyIndex":0,"enemyValid":false,"switchId":1,"switchValid":false,"turnA":0,"turnB":0,"turnEnding":true,"turnValid":false},"list":[{"code":111,"indent":0,"parameters":[4,10,0]},{"code":117,"indent":1,"parameters":[101]},{"code":0,"indent":1,"parameters":[]},{"code":411,"indent":0,"parameters":[]},{"code":115,"indent":1,"parameters":[]},{"code":0,"indent":1,"parameters":[]},{"code":412,"indent":0,"parameters":[]},{"code":0,"indent":0,"parameters":[]}],"span":1}]},
{"id":6,"members":[{"enemyId":3,"x":144,"y":464,"hidden":false},{"enemyId":4,"x":352,"y":672,"hidden":false},{"enemyId":5,"x":416,"y":512,"hidden":false},{"enemyId":2,"x":96,"y":624,"hidden":false}],"name":"Medium Troops 1","pages":[{"conditions":{"actorHp":50,"actorId":1,"actorValid":false,"enemyHp":50,"enemyIndex":0,"enemyValid":false,"switchId":1,"switchValid":false,"turnA":0,"turnB":0,"turnEnding":true,"turnValid":false},"list":[{"code":111,"indent":0,"parameters":[4,10,0]},{"code":117,"indent":1,"parameters":[101]},{"code":0,"indent":1,"parameters":[]},{"code":411,"indent":0,"parameters":[]},{"code":115,"indent":1,"parameters":[]},{"code":0,"indent":1,"parameters":[]},{"code":412,"indent":0,"parameters":[]},{"code":0,"indent":0,"parameters":[]}],"span":1}]},
{"id":7,"members":[{"enemyId":5,"x":352,"y":672,"hidden":false},{"enemyId":5,"x":416,"y":512,"hidden":false},{"enemyId":2,"x":128,"y":464,"hidden":false},{"enemyId":2,"x":96,"y":624,"hidden":false}],"name":"Medium Troops 2","pages":[{"conditions":{"actorHp":50,"actorId":1,"actorValid":false,"enemyHp":50,"enemyIndex":0,"enemyValid":false,"switchId":1,"switchValid":false,"turnA":0,"turnB":0,"turnEnding":true,"turnValid":false},"list":[{"code":111,"indent":0,"parameters":[4,10,0]},{"code":117,"indent":1,"parameters":[101]},{"code":0,"indent":1,"parameters":[]},{"code":411,"indent":0,"parameters":[]},{"code":115,"indent":1,"parameters":[]},{"code":0,"indent":1,"parameters":[]},{"code":412,"indent":0,"parameters":[]},{"code":0,"indent":0,"parameters":[]}],"span":1}]},
{"id":8,"members":[{"enemyId":6,"x":96,"y":608,"hidden":false},{"enemyId":6,"x":400,"y":512,"hidden":false},{"enemyId":4,"x":352,"y":672,"hidden":false},{"enemyId":3,"x":144,"y":464,"hidden":false}],"name":"Medium Troops 3","pages":[{"conditions":{"actorHp":50,"actorId":1,"actorValid":false,"enemyHp":50,"enemyIndex":0,"enemyValid":false,"switchId":1,"switchValid":false,"turnA":0,"turnB":0,"turnEnding":true,"turnValid":false},"list":[{"code":111,"indent":0,"parameters":[4,10,0]},{"code":117,"indent":1,"parameters":[101]},{"code":0,"indent":1,"parameters":[]},{"code":411,"indent":0,"parameters":[]},{"code":115,"indent":1,"parameters":[]},{"code":0,"indent":1,"parameters":[]},{"code":412,"indent":0,"parameters":[]},{"code":0,"indent":0,"parameters":[]}],"span":1}]},
{"id":9,"members":[{"enemyId":5,"x":160,"y":688,"hidden":false},{"enemyId":5,"x":192,"y":480,"hidden":false},{"enemyId":4,"x":448,"y":592,"hidden":false}],"name":"Medium Troops 4","pages":[{"conditions":{"actorHp":50,"actorId":1,"actorValid":false,"enemyHp":50,"enemyIndex":0,"enemyValid":false,"switchId":1,"switchValid":false,"turnA":0,"turnB":0,"turnEnding":true,"turnValid":false},"list":[{"code":111,"indent":0,"parameters":[4,10,0]},{"code":117,"indent":1,"parameters":[101]},{"code":0,"indent":1,"parameters":[]},{"code":411,"indent":0,"parameters":[]},{"code":115,"indent":1,"parameters":[]},{"code":0,"indent":1,"parameters":[]},{"code":412,"indent":0,"parameters":[]},{"code":0,"indent":0,"parameters":[]}],"span":1}]},
{"id":10,"members":[{"enemyId":6,"x":96,"y":608,"hidden":false},{"enemyId":4,"x":352,"y":672,"hidden":false},{"enemyId":3,"x":144,"y":464,"hidden":false},{"enemyId":4,"x":416,"y":528,"hidden":false}],"name":"Medium Troops 5","pages":[{"conditions":{"actorHp":50,"actorId":1,"actorValid":false,"enemyHp":50,"enemyIndex":0,"enemyValid":false,"switchId":1,"switchValid":false,"turnA":0,"turnB":0,"turnEnding":true,"turnValid":false},"list":[{"code":111,"indent":0,"parameters":[4,10,0]},{"code":117,"indent":1,"parameters":[101]},{"code":0,"indent":1,"parameters":[]},{"code":411,"indent":0,"parameters":[]},{"code":115,"indent":1,"parameters":[]},{"code":0,"indent":1,"parameters":[]},{"code":412,"indent":0,"parameters":[]},{"code":0,"indent":0,"parameters":[]}],"span":1}]},
{"id":11,"members":[{"enemyId":5,"x":416,"y":512,"hidden":false},{"enemyId":8,"x":160,"y":496,"hidden":false},{"enemyId":7,"x":320,"y":656,"hidden":false},{"enemyId":6,"x":96,"y":608,"hidden":false}],"name":"Hard Troops 1","pages":[{"conditions":{"actorHp":50,"actorId":1,"actorValid":false,"enemyHp":50,"enemyIndex":0,"enemyValid":false,"switchId":1,"switchValid":false,"turnA":0,"turnB":0,"turnEnding":true,"turnValid":false},"list":[{"code":111,"indent":0,"parameters":[4,10,0]},{"code":117,"indent":1,"parameters":[101]},{"code":0,"indent":1,"parameters":[]},{"code":411,"indent":0,"parameters":[]},{"code":115,"indent":1,"parameters":[]},{"code":0,"indent":1,"parameters":[]},{"code":412,"indent":0,"parameters":[]},{"code":0,"indent":0,"parameters":[]}],"span":1}]},
{"id":12,"members":[{"enemyId":7,"x":320,"y":656,"hidden":false},{"enemyId":8,"x":160,"y":496,"hidden":false},{"enemyId":1,"x":384,"y":512,"hidden":false},{"enemyId":2,"x":80,"y":624,"hidden":false}],"name":"Hard Troops 2","pages":[{"conditions":{"actorHp":50,"actorId":1,"actorValid":false,"enemyHp":50,"enemyIndex":0,"enemyValid":false,"switchId":1,"switchValid":false,"turnA":0,"turnB":0,"turnEnding":true,"turnValid":false},"list":[{"code":111,"indent":0,"parameters":[4,10,0]},{"code":117,"indent":1,"parameters":[101]},{"code":0,"indent":1,"parameters":[]},{"code":411,"indent":0,"parameters":[]},{"code":115,"indent":1,"parameters":[]},{"code":0,"indent":1,"parameters":[]},{"code":412,"indent":0,"parameters":[]},{"code":0,"indent":0,"parameters":[]}],"span":1}]},
{"id":13,"members":[{"enemyId":8,"x":160,"y":496,"hidden":false},{"enemyId":7,"x":432,"y":528,"hidden":false},{"enemyId":7,"x":368,"y":672,"hidden":false},{"enemyId":8,"x":96,"y":672,"hidden":false}],"name":"Hard Troops 3","pages":[{"conditions":{"actorHp":50,"actorId":1,"actorValid":false,"enemyHp":50,"enemyIndex":0,"enemyValid":false,"switchId":1,"switchValid":false,"turnA":0,"turnB":0,"turnEnding":true,"turnValid":false},"list":[{"code":111,"indent":0,"parameters":[4,10,0]},{"code":117,"indent":1,"parameters":[101]},{"code":0,"indent":1,"parameters":[]},{"code":411,"indent":0,"parameters":[]},{"code":115,"indent":1,"parameters":[]},{"code":0,"indent":1,"parameters":[]},{"code":412,"indent":0,"parameters":[]},{"code":0,"indent":0,"parameters":[]}],"span":1}]},
{"id":14,"members":[{"enemyId":7,"x":80,"y":612,"hidden":false},{"enemyId":6,"x":336,"y":656,"hidden":false},{"enemyId":3,"x":144,"y":464,"hidden":false},{"enemyId":6,"x":400,"y":512,"hidden":false}],"name":"Hard Troops 4","pages":[{"conditions":{"actorHp":50,"actorId":1,"actorValid":false,"enemyHp":50,"enemyIndex":0,"enemyValid":false,"switchId":1,"switchValid":false,"turnA":0,"turnB":0,"turnEnding":true,"turnValid":false},"list":[{"code":111,"indent":0,"parameters":[4,10,0]},{"code":117,"indent":1,"parameters":[101]},{"code":0,"indent":1,"parameters":[]},{"code":411,"indent":0,"parameters":[]},{"code":115,"indent":1,"parameters":[]},{"code":0,"indent":1,"parameters":[]},{"code":412,"indent":0,"parameters":[]},{"code":0,"indent":0,"parameters":[]}],"span":1}]},
{"id":15,"members":[{"enemyId":8,"x":97,"y":672,"hidden":false},{"enemyId":8,"x":160,"y":496,"hidden":false},{"enemyId":8,"x":464,"y":528,"hidden":false},{"enemyId":8,"x":400,"y":704,"hidden":false}],"name":"Hard Troops 5","pages":[{"conditions":{"actorHp":50,"actorId":1,"actorValid":false,"enemyHp":50,"enemyIndex":0,"enemyValid":false,"switchId":1,"switchValid":false,"turnA":0,"turnB":0,"turnEnding":true,"turnValid":false},"list":[{"code":111,"indent":0,"parameters":[4,10,0]},{"code":117,"indent":1,"parameters":[101]},{"code":0,"indent":1,"parameters":[]},{"code":411,"indent":0,"parameters":[]},{"code":115,"indent":1,"parameters":[]},{"code":0,"indent":1,"parameters":[]},{"code":412,"indent":0,"parameters":[]},{"code":0,"indent":0,"parameters":[]}],"span":1}]},
{"id":16,"members":[{"enemyId":9,"x":308,"y":544,"hidden":false}],"name":"Boss Battle","pages":[{"conditions":{"actorHp":50,"actorId":1,"actorValid":false,"enemyHp":50,"enemyIndex":0,"enemyValid":false,"switchId":1,"switchValid":false,"turnA":0,"turnB":0,"turnEnding":false,"turnValid":false},"list":[{"code":0,"indent":0,"parameters":[]}],"span":0}]},
{"id":17,"members":[{"enemyId":10,"x":371,"y":800,"hidden":false}],"name":"Alien Warrior","pages":[{"conditions":{"actorHp":50,"actorId":1,"actorValid":false,"enemyHp":50,"enemyIndex":0,"enemyValid":false,"switchId":1,"switchValid":false,"turnA":0,"turnB":0,"turnEnding":false,"turnValid":false},"list":[{"code":0,"indent":0,"parameters":[]}],"span":0}]},
{"id":18,"members":[{"enemyId":6,"x":377,"y":576,"hidden":false},{"enemyId":6,"x":609,"y":744,"hidden":false}],"name":"test","pages":[{"conditions":{"actorHp":50,"actorId":1,"actorValid":false,"enemyHp":50,"enemyIndex":0,"enemyValid":false,"switchId":1,"switchValid":false,"turnA":0,"turnB":0,"turnEnding":false,"turnValid":false},"list":[{"code":0,"indent":0,"parameters":[]}],"span":0}]},
{"id":19,"members":[{"enemyId":2,"x":413,"y":320,"hidden":false},{"enemyId":4,"x":399,"y":656,"hidden":false},{"enemyId":5,"x":224,"y":784,"hidden":false},{"enemyId":7,"x":405,"y":877,"hidden":false},{"enemyId":8,"x":222,"y":512,"hidden":false},{"enemyId":16,"x":616,"y":611,"hidden":false}],"name":"TEST 2","pages":[{"conditions":{"actorHp":50,"actorId":1,"actorValid":false,"enemyHp":50,"enemyIndex":0,"enemyValid":false,"switchId":1,"switchValid":false,"turnA":0,"turnB":0,"turnEnding":false,"turnValid":false},"list":[{"code":0,"indent":0,"parameters":[]}],"span":1}]},
{"id":20,"members":[],"name":"","pages":[{"conditions":{"actorHp":50,"actorId":1,"actorValid":false,"enemyHp":50,"enemyIndex":0,"enemyValid":false,"switchId":1,"switchValid":false,"turnA":0,"turnB":0,"turnEnding":false,"turnValid":false},"list":[{"code":0,"indent":0,"parameters":[]}],"span":0}]}
]